thepricer_utils/__init__.py
thepricer_utils-0.0.1.dist-info/METADATA
thepricer_utils-0.0.1.dist-info/WHEEL
thepricer_utils-0.0.1.dist-info/licenses/LICENSE
thepricer_utils-0.0.1.dist-info/RECORD
