Metadata-Version: 2.4
Name: thepricer-utils
Version: 0.0.1
Summary: Tiny helpers for price explainers (formatting, ranges, hours-to-afford).
Project-URL: Homepage, https://www.thepricer.org/
Project-URL: Newsroom, https://www.thepricer.org/press
Project-URL: Documentation, https://www.thepricer.org/
Author-email: Alec Pow <press@thepricer.org>
License: MIT
License-File: LICENSE
Keywords: affordability,consumer,cost,prices,pricing,thepricer
Classifier: Intended Audience :: Information Technology
Classifier: License :: OSI Approved :: MIT License
Classifier: Programming Language :: Python :: 3
Classifier: Topic :: Internet :: WWW/HTTP
Classifier: Topic :: Office/Business :: Financial
Requires-Python: >=3.8
